mask_stats/__init__.py
mask_stats/_overlap.py
mask_stats/_surface_distance.py
mask_stats/mask_stats.py
mask_stats/__pycache__/__init__.cpython-38.pyc
mask_stats/__pycache__/_overlap.cpython-38.pyc
mask_stats/__pycache__/_surface_distance.cpython-38.pyc
mask_stats/__pycache__/mask_stats.cpython-38.pyc
mask_stats-0.3.0.dist-info/AUTHORS.rst
mask_stats-0.3.0.dist-info/LICENSE
mask_stats-0.3.0.dist-info/METADATA
mask_stats-0.3.0.dist-info/WHEEL
mask_stats-0.3.0.dist-info/top_level.txt
mask_stats-0.3.0.dist-info/RECORD
