Metadata-Version: 2.1
Name: mask-stats
Version: 0.3.0
Summary: Compute summary statistics between two binary masks.
Home-page: https://github.com/yngvem/mask_stats
Author: Yngve Mardal Moe
Author-email: yngve.m.moe@gmail.com
License: "MIT license",
Keywords: mask_stats
Platform: UNKNOWN
Classifier: Development Status :: 2 - Pre-Alpha
Classifier: Intended Audience :: Developers
Classifier: License :: OSI Approved :: MIT License
Classifier: Natural Language :: English
Classifier: Programming Language :: Python :: 3.6
Classifier: Programming Language :: Python :: 3.7
Requires-Dist: numpy
Requires-Dist: scipy
Requires-Dist: tqdm
